Metadata-Version: 2.1
Name: OWR
Version: 0.4.0
Summary: Obscene word recognition package
Home-page: https://github.com/VladVslv/OWR
Author: Vlad Vasilev
Author-email: vpvasilev.work@gmail.com
License: GNU GENERAL PUBLIC LICENSE
Platform: UNKNOWN
License-File: LICENSE
